verification/checker.sv
module checker(
    input  logic        dest_clk,
    input  logic        dest_reset_n,
    input  logic        dest_strobe,
    output logic [31:0] error_count
);
    initial begin
        error_count = 0;
    end

    always @(posedge dest_clk) begin
        if (!dest_reset_n) begin
            // Reset error counter on reset
            error_count <= 0;
        end else if (dest_strobe) begin
            // Check logic for strobe signal, increase error count if incorrect
            // Assuming some condition checks for now
            error_count <= error_count + 1; // Simplistic error checking
        end
    end
endmodule

verification/stimulus.sv
module stimulus(
    output logic source_clk,
    output logic source_reset_n,
    output logic source_strobe,
    input  logic source_stall,
    output logic dest_clk,
    output logic dest_reset_n,
    input  logic dest_strobe,
    output logic dest_stall
);
    initial begin
        source_clk = 0;
        dest_clk = 0;
        source_reset_n = 0;
        dest_reset_n = 0;
        source_strobe = 0;
        dest_stall = 0;
        // Reset sequence
        #20 source_reset_n = 1;
        dest_reset_n = 1;

        // Generate a single clock pulse
        @(posedge source_clk);
        source_strobe = 1;
        @(posedge source_clk);
        source_strobe = 0;

        // Vary clock speed for the next test after a delay
        #1000;
        source_clk = 0;
        dest_clk = 0;
        repeat (2) begin
            #7 source_clk = ~source_clk;  // Approximately 71 MHz
            #13 dest_clk = ~dest_clk;    // Approximately 38 MHz
        end
    end

    // Clock generation logic for source and destination
    always #5 source_clk = ~source_clk;  // Default 100 MHz
    always #10 dest_clk = ~dest_clk;    // Default 50 MHz
endmodule

hdl/cdc_handshake_ss.sv
`timescale 1ns / 1ps

module cdc_handshake_ss (
    input  logic source_clk,
    input  logic source_reset_n,
    input  logic source_strobe,
    output logic source_stall,
    input  logic dest_clk,
    input  logic dest_reset_n,
    output logic dest_strobe,
    input  logic dest_stall
);

    // Internal Signals / Synchronization registers
    logic pulse_stretched, pulse_registered;
    logic source_strobe_sync1, source_strobe_sync2, source_stall_sync;

    // Stretch pulse for clock domain crossing
    always_ff @(posedge source_clk or negedge source_reset_n) begin
        if (!source_reset_n) begin
            pulse_stretched   <= 1'b0;
            source_stall_sync <= 1'b1;
            source_stall      <= 1'b1;
        end else begin
            // Reflect stall condition back to the source domain
            source_stall_sync <= dest_stall;
            source_stall      <= source_stall_sync;
            // Stretch incoming pulse as long as there is stall
            if (source_strobe && !pulse_stretched) begin
                pulse_stretched <= 1'b1;  // Stretch the pulse until acknowledged
            end else if (!source_stall) begin
                pulse_stretched <= 1'b0;  // Reset the pulse on stall or ack
            end
        end
    end

    // Synchronize stretched pulse to destination domain
    always_ff @(posedge dest_clk or negedge dest_reset_n) begin
        if (!dest_reset_n) begin
            source_strobe_sync1 <= 1'b0;
            source_strobe_sync2 <= 1'b0;
            dest_strobe         <= 1'b0;
        end else begin
            // Default values
            dest_strobe         <= 1'b0;
            // 2-FF Synchronizer
            source_strobe_sync1 <= pulse_stretched;
            source_strobe_sync2 <= source_strobe_sync1;
            // Destination logic
            if (!dest_strobe && source_strobe_sync2 && dest_stall) begin
                dest_strobe     <= 1'b1;  // Register pulse on first detection
            end
        end
    end

endmodule

verification/tb_cdc_handshake_ss.sv
module tb_cdc_handshake_ss;
    wire source_clk, source_reset_n, source_strobe, source_stall;
    wire dest_clk, dest_reset_n, dest_strobe, dest_stall;

    // Instantiate DUT
    cdc_handshake_ss DUT (
        .source_clk(source_clk),
        .source_reset_n(source_reset_n),
        .source_strobe(source_strobe),
        .source_stall(source_stall),
        .dest_clk(dest_clk),
        .dest_reset_n(dest_reset_n),
        .dest_strobe(dest_strobe),
        .dest_stall(dest_stall)
    );

    // Instantiate stimulus
    stimulus stimulus_inst(
        .source_clk(source_clk),
        .source_reset_n(source_reset_n),
        .source_strobe(source_strobe),
        .source_stall(source_stall),
        .dest_clk(dest_clk),
        .dest_reset_n(dest_reset_n),
        .dest_strobe(dest_strobe),
        .dest_stall(dest_stall)
    );

    // Instantiate checker
    wire [31:0] error_count;
    checker checker_inst(
        .dest_clk(dest_clk),
        .dest_reset_n(dest_reset_n),
        .dest_strobe(dest_strobe),
        .error_count(error_count)
    );

    // Monitoring and finishing condition
    initial begin
        $monitor("Time=%t, source_strobe=%b, dest_strobe=%b, Errors=%d", $time, source_strobe, dest_strobe, error_count);
        #2000;
        $finish;
    end
endmodule

verification/questa/full.vcd
$date
	Sun Jul 21 14:14:46 2024
$end
$version
	QuestaSim Version 2021.1
$end
$timescale
	1ps
$end
$scope module tb_cdc_handshake_ss $end
$scope module stimulus_inst $end
$var wire 1 ! dest_strobe $end
$upscope $end
$upscope $end
$enddefinitions $end
#0
0!
0!
#190000
1!
#210000
0!
#330000
1!
#350000
0!
#470000
1!
#490000
0!
#610000
1!
#630000
0!
#750000
1!
#770000
0!
#8220000
1!
#8860000
0!
#15260000
1!
#15900000
0!
#21020000
1!
#21660000
0!
#28060000
1!
#28700000
0!
#33820000
1!
#34460000
0!
#39362500
1!
#39407500
0!
#39947500
1!
#39992500
0!
#40577500
1!
#40622500
0!
#41162500
1!
#41207500
0!
#41792500
1!
#41837500
0!
#49582500
1!
#50171500
0!
#56650500
1!
#57239500
0!
#63718500
1!
#64307500
0!
#70786500
1!
#71375500
0!
#77854500
1!
#78443500
0!
#85957000
1!
#86101000
0!
#88981000
1!
#89125000
0!
#91573000
1!
#91717000
0!
#94597000
1!
#94741000
0!
#97189000
1!
#97333000
0!
#103576000
1!
#103958000
0!
#107014000
1!
#107396000
0!
#110834000
1!
#111216000
0!
#115036000
1!
#115418000
0!
#118856000
1!
#119238000
0!
#125962500
1!
#126055500
0!
#129589500
1!
#129682500
0!
#133216500
1!
#133309500
0!
#136936500
1!
#137029500
0!
#140563500
1!
#140656500
0!
#150289500
1!
#151220500
0!
#155875500
1!
#156806500
0!
#161461500
1!
#162392500
0!
#167047500
1!
#167978500
0!
#172633500
1!
#173564500
0!
#183368500
1!
#184057500
0!
#189569500
1!
#190258500
0!
#195770500
1!
#196459500
0!
#201971500
1!
#202660500
0!
#208172500
1!
#208861500
0!
#217474000
1!
#217488000
0!
#222346000
1!
#222360000
0!
#227218000
1!
#227232000
0!
#232090000
1!
#232104000
0!
#236962000
1!
#236976000
0!
#246278000
1!
#246520000
0!
#251118000
1!
#251360000
0!
#255958000
1!
#256200000
0!
#260798000
1!
#261040000
0!
#265638000
1!
#265880000
0!
#271760000
1!
#271786000
0!
#273892000
1!
#273918000
0!
#276024000
1!
#276050000
0!
#278130000
1!
#278156000
0!
#280262000
1!
#280288000
0!
#289902500
1!
#290743500
0!
#295789500
1!
#296630500
0!
#301676500
1!
#302517500
0!
#307563500
1!
#308404500
0!
#313450500
1!
#314291500
0!
#325088500
1!
#326023500
0!
#330698500
1!
#331633500
0!
#337243500
1!
#338178500
0!
#343788500
1!
#344723500
0!
#350333500
1!
#351268500
0!
#357628500
1!
#357953500
0!
#361203500
1!
#361528500
0!
#364778500
1!
#365103500
0!
#367703500
1!
#368028500
0!
#371278500
1!
#371603500
0!
#379743000
1!
#379989000
0!
#384663000
1!
#384909000
0!
#390321000
1!
#390567000
0!
#395241000
1!
#395487000
0!
#400161000
1!
#400407000
0!
#409203000
1!
#409933000
0!
#413583000
1!
#414313000
0!
#417963000
1!
#418693000
0!
#422343000
1!
#423073000
0!
#426723000
1!
#427453000
0!
#430320000
1!
#430368000
0!
#430608000
1!
#430656000
0!
#430896000
1!
#430944000
0!
#431184000
1!
#431232000
0!
#431472000
1!
#431520000
0!
#439255000
1!
#439913000
0!
#446493000
1!
#447151000
0!
#452415000
1!
#453073000
0!
#459653000
1!
#460311000
0!
#466891000
1!
#467549000
0!
#477504500
1!
#478171500
0!
#483507500
1!
#484174500
0!
#490177500
1!
#490844500
0!
#496847500
1!
#497514500
0!
#503517500
1!
#504184500
0!
#514240000
1!
#515120000
0!
#519520000
1!
#520400000
0!
#524800000
1!
#525680000
0!
#530080000
1!
#530960000
0!
#535360000
1!
#536240000
0!
#544065000
1!
#544075000
0!
#549065000
1!
#549075000
0!
#554065000
1!
#554075000
0!
#559065000
1!
#559075000
0!
#564065000
1!
#564075000
0!
#574560000
1!
#575560000
0!
#580560000
1!
#581560000
0!
#586560000
1!
#587560000
0!
#592560000
1!
#593560000
0!
#598560000
1!
#599560000
0!
